hcloud_rdns_manager/__init__.py
hcloud_rdns_manager/deployment.py
hcloud_rdns_manager/export.py
hcloud_rdns_manager/hcloudapi.py
hcloud_rdns_manager/main.py
hcloud_rdns_manager/validation.py
hcloud_rdns_manager/misc/rdns-zones.example.yml
hcloud_rdns_manager-1.0.0.dist-info/METADATA
hcloud_rdns_manager-1.0.0.dist-info/WHEEL
hcloud_rdns_manager-1.0.0.dist-info/entry_points.txt
hcloud_rdns_manager-1.0.0.dist-info/licenses/LICENSE
hcloud_rdns_manager-1.0.0.dist-info/RECORD
