Metadata-Version: 2.4
Name: hcloud-rdns-manager
Version: 1.0.0
Summary: The hcloud-rdns-manager - the smart way to manage your rDNS records in the Hetzner cloud
Project-URL: Homepage, https://codeberg.org/wh0ami/hcloud-rdns-manager
Project-URL: Documentation, https://codeberg.org/wh0ami/hcloud-rdns-manager/src/branch/master/README.md
Project-URL: Repository, https://codeberg.org/wh0ami/hcloud-rdns-manager
Project-URL: Issues, https://codeberg.org/wh0ami/hcloud-rdns-manager/issues
Author-email: wh0ami <wh0ami@noreply.codeberg.org>
License: Copyright (c) 2025 wh0ami
License-File: LICENSE
Keywords: Automation,Cloud,DNS,Hetzner,IaC,Infrastructure as Code,PTR,rDNS
Classifier: Development Status :: 5 - Production/Stable
Classifier: Environment :: Console
Classifier: License :: OSI Approved :: MIT License
Classifier: Programming Language :: Python :: 3
Requires-Python: >=3.13
Requires-Dist: hcloud>=2.3.0
Requires-Dist: jsonschema>=4.23.0
Requires-Dist: loguru>=0.7.3
Requires-Dist: pyyaml>=6.0.2
Requires-Dist: tabulate>=0.9.0
